teedoc_plugin_jupyter_notebook_parser/__init__.py
teedoc_plugin_jupyter_notebook_parser/jupyter_convert.py
teedoc_plugin_jupyter_notebook_parser/templates/lab/base.html.j2
teedoc_plugin_jupyter_notebook_parser/templates/lab/conf.json
teedoc_plugin_jupyter_notebook_parser/templates/lab/index.html.j2
teedoc_plugin_jupyter_notebook_parser/templates/lab/static/index.css
teedoc_plugin_jupyter_notebook_parser/templates/lab/static/theme-dark.css
teedoc_plugin_jupyter_notebook_parser/templates/lab/static/theme-light.css
teedoc_plugin_jupyter_notebook_parser-1.4.0.dist-info/LICENSE
teedoc_plugin_jupyter_notebook_parser-1.4.0.dist-info/METADATA
teedoc_plugin_jupyter_notebook_parser-1.4.0.dist-info/WHEEL
teedoc_plugin_jupyter_notebook_parser-1.4.0.dist-info/top_level.txt
teedoc_plugin_jupyter_notebook_parser-1.4.0.dist-info/RECORD
