Metadata-Version: 2.1
Name: teedoc-plugin-jupyter-notebook-parser
Version: 1.4.0
Summary: doc website generator
Home-page: https://github.com/Neutree/teedoc
Author: Neucrack
Author-email: CZD666666@gmail.com
License: MIT
Keywords: doc website markdown jupyter notbook generator
Platform: UNKNOWN
Classifier: Intended Audience :: Developers
Classifier: License :: OSI Approved :: MIT License
Classifier: Programming Language :: Python :: 3
License-File: LICENSE
Requires-Dist: PyYaml (>=5.4.1)
Requires-Dist: jupyter-core (>=4.11.1)
Requires-Dist: nbconvert (>=7.0.0)
